[
  {
    "type": "constructor",
    "inputs": [],
    "stateMutability": "nonpayable"
  },
  {
    "type": "function",
    "name": "MAX_SUPPLY",
    "inputs": [],
    "outputs": [
      {
        "name": "",
        "type": "uint256",
        "internalType": "uint256"
      }
    ],
    "stateMutability": "view"
  },
  {
    "type": "function",
    "name": "burnXpegs",
    "inputs": [
      {
        "name": "from",
        "type": "address",
        "internalType": "address"
      },
      {
        "name": "qty",
        "type": "uint256",
        "internalType": "uint256"
      }
    ],
    "outputs": [],
    "stateMutability": "nonpayable"
  },
  {
    "type": "function",
    "name": "deployer",
    "inputs": [],
    "outputs": [
      {
        "name": "",
        "type": "address",
        "internalType": "address"
      }
    ],
    "stateMutability": "view"
  },
  {
    "type": "function",
    "name": "holdersCount",
    "inputs": [],
    "outputs": [
      {
        "name": "",
        "type": "uint256",
        "internalType": "uint256"
      }
    ],
    "stateMutability": "view"
  },
  {
    "type": "function",
    "name": "isHolder",
    "inputs": [
      {
        "name": "owner",
        "type": "address",
        "internalType": "address"
      }
    ],
    "outputs": [
      {
        "name": "",
        "type": "bool",
        "internalType": "bool"
      }
    ],
    "stateMutability": "view"
  },
  {
    "type": "function",
    "name": "isOwnerOf",
    "inputs": [
      {
        "name": "owner",
        "type": "address",
        "internalType": "address"
      },
      {
        "name": "id",
        "type": "uint256",
        "internalType": "uint256"
      }
    ],
    "outputs": [
      {
        "name": "",
        "type": "bool",
        "internalType": "bool"
      }
    ],
    "stateMutability": "view"
  },
  {
    "type": "function",
    "name": "market",
    "inputs": [],
    "outputs": [
      {
        "name": "",
        "type": "address",
        "internalType": "address"
      }
    ],
    "stateMutability": "view"
  },
  {
    "type": "function",
    "name": "marketTransfer",
    "inputs": [
      {
        "name": "from",
        "type": "address",
        "internalType": "address"
      },
      {
        "name": "to",
        "type": "address",
        "internalType": "address"
      },
      {
        "name": "id",
        "type": "uint256",
        "internalType": "uint256"
      }
    ],
    "outputs": [],
    "stateMutability": "nonpayable"
  },
  {
    "type": "function",
    "name": "mintXpegs",
    "inputs": [
      {
        "name": "to",
        "type": "address",
        "internalType": "address"
      },
      {
        "name": "qty",
        "type": "uint256",
        "internalType": "uint256"
      },
      {
        "name": "entropy",
        "type": "uint256",
        "internalType": "uint256"
      }
    ],
    "outputs": [],
    "stateMutability": "nonpayable"
  },
  {
    "type": "function",
    "name": "moveXpegs",
    "inputs": [
      {
        "name": "from",
        "type": "address",
        "internalType": "address"
      },
      {
        "name": "to",
        "type": "address",
        "internalType": "address"
      },
      {
        "name": "qty",
        "type": "uint256",
        "internalType": "uint256"
      }
    ],
    "outputs": [],
    "stateMutability": "nonpayable"
  },
  {
    "type": "function",
    "name": "ownerOf",
    "inputs": [
      {
        "name": "id",
        "type": "uint256",
        "internalType": "uint256"
      }
    ],
    "outputs": [
      {
        "name": "",
        "type": "address",
        "internalType": "address"
      }
    ],
    "stateMutability": "view"
  },
  {
    "type": "function",
    "name": "ownerXpegAt",
    "inputs": [
      {
        "name": "owner",
        "type": "address",
        "internalType": "address"
      },
      {
        "name": "index",
        "type": "uint256",
        "internalType": "uint256"
      }
    ],
    "outputs": [
      {
        "name": "id",
        "type": "uint256",
        "internalType": "uint256"
      },
      {
        "name": "seed",
        "type": "uint256",
        "internalType": "uint256"
      }
    ],
    "stateMutability": "view"
  },
  {
    "type": "function",
    "name": "ownerXpegsCount",
    "inputs": [
      {
        "name": "owner",
        "type": "address",
        "internalType": "address"
      }
    ],
    "outputs": [
      {
        "name": "",
        "type": "uint256",
        "internalType": "uint256"
      }
    ],
    "stateMutability": "view"
  },
  {
    "type": "function",
    "name": "ownerXpegsPage",
    "inputs": [
      {
        "name": "owner",
        "type": "address",
        "internalType": "address"
      },
      {
        "name": "page",
        "type": "uint256",
        "internalType": "uint256"
      },
      {
        "name": "pageSize",
        "type": "uint256",
        "internalType": "uint256"
      }
    ],
    "outputs": [
      {
        "name": "ids",
        "type": "uint256[]",
        "internalType": "uint256[]"
      },
      {
        "name": "seeds",
        "type": "uint256[]",
        "internalType": "uint256[]"
      }
    ],
    "stateMutability": "view"
  },
  {
    "type": "function",
    "name": "renderer",
    "inputs": [],
    "outputs": [
      {
        "name": "",
        "type": "address",
        "internalType": "address"
      }
    ],
    "stateMutability": "view"
  },
  {
    "type": "function",
    "name": "setHumansToken",
    "inputs": [
      {
        "name": "_token",
        "type": "address",
        "internalType": "address"
      }
    ],
    "outputs": [],
    "stateMutability": "nonpayable"
  },
  {
    "type": "function",
    "name": "setMarket",
    "inputs": [
      {
        "name": "_market",
        "type": "address",
        "internalType": "address"
      }
    ],
    "outputs": [],
    "stateMutability": "nonpayable"
  },
  {
    "type": "function",
    "name": "setRenderer",
    "inputs": [
      {
        "name": "_renderer",
        "type": "address",
        "internalType": "address"
      }
    ],
    "outputs": [],
    "stateMutability": "nonpayable"
  },
  {
    "type": "function",
    "name": "tokenURI",
    "inputs": [
      {
        "name": "id",
        "type": "uint256",
        "internalType": "uint256"
      }
    ],
    "outputs": [
      {
        "name": "",
        "type": "string",
        "internalType": "string"
      }
    ],
    "stateMutability": "view"
  },
  {
    "type": "function",
    "name": "totalAlive",
    "inputs": [],
    "outputs": [
      {
        "name": "",
        "type": "uint256",
        "internalType": "uint256"
      }
    ],
    "stateMutability": "view"
  },
  {
    "type": "function",
    "name": "totalMinted",
    "inputs": [],
    "outputs": [
      {
        "name": "",
        "type": "uint256",
        "internalType": "uint256"
      }
    ],
    "stateMutability": "view"
  },
  {
    "type": "function",
    "name": "transferXpeg",
    "inputs": [
      {
        "name": "to",
        "type": "address",
        "internalType": "address"
      },
      {
        "name": "id",
        "type": "uint256",
        "internalType": "uint256"
      }
    ],
    "outputs": [],
    "stateMutability": "nonpayable"
  },
  {
    "type": "function",
    "name": "transferXpegList",
    "inputs": [
      {
        "name": "to",
        "type": "address",
        "internalType": "address"
      },
      {
        "name": "ids",
        "type": "uint256[]",
        "internalType": "uint256[]"
      }
    ],
    "outputs": [],
    "stateMutability": "nonpayable"
  },
  {
    "type": "function",
    "name": "xpegToken",
    "inputs": [],
    "outputs": [
      {
        "name": "",
        "type": "address",
        "internalType": "address"
      }
    ],
    "stateMutability": "view"
  },
  {
    "type": "function",
    "name": "xpegs",
    "inputs": [
      {
        "name": "",
        "type": "uint256",
        "internalType": "uint256"
      }
    ],
    "outputs": [
      {
        "name": "seed",
        "type": "uint256",
        "internalType": "uint256"
      },
      {
        "name": "mintTimestamp",
        "type": "uint64",
        "internalType": "uint64"
      }
    ],
    "stateMutability": "view"
  },
  {
    "type": "event",
    "name": "HumansTokenSet",
    "inputs": [
      {
        "name": "token",
        "type": "address",
        "indexed": true,
        "internalType": "address"
      }
    ],
    "anonymous": false
  },
  {
    "type": "event",
    "name": "MarketSet",
    "inputs": [
      {
        "name": "market",
        "type": "address",
        "indexed": true,
        "internalType": "address"
      }
    ],
    "anonymous": false
  },
  {
    "type": "event",
    "name": "RendererSet",
    "inputs": [
      {
        "name": "renderer",
        "type": "address",
        "indexed": true,
        "internalType": "address"
      }
    ],
    "anonymous": false
  },
  {
    "type": "event",
    "name": "XpegBurned",
    "inputs": [
      {
        "name": "from",
        "type": "address",
        "indexed": true,
        "internalType": "address"
      },
      {
        "name": "id",
        "type": "uint256",
        "indexed": true,
        "internalType": "uint256"
      }
    ],
    "anonymous": false
  },
  {
    "type": "event",
    "name": "XpegMinted",
    "inputs": [
      {
        "name": "to",
        "type": "address",
        "indexed": true,
        "internalType": "address"
      },
      {
        "name": "id",
        "type": "uint256",
        "indexed": true,
        "internalType": "uint256"
      },
      {
        "name": "seed",
        "type": "uint256",
        "indexed": false,
        "internalType": "uint256"
      }
    ],
    "anonymous": false
  },
  {
    "type": "event",
    "name": "XpegMoved",
    "inputs": [
      {
        "name": "from",
        "type": "address",
        "indexed": true,
        "internalType": "address"
      },
      {
        "name": "to",
        "type": "address",
        "indexed": true,
        "internalType": "address"
      },
      {
        "name": "id",
        "type": "uint256",
        "indexed": true,
        "internalType": "uint256"
      }
    ],
    "anonymous": false
  },
  {
    "type": "error",
    "name": "MarketAlreadySet",
    "inputs": []
  },
  {
    "type": "error",
    "name": "MaxSupplyReached",
    "inputs": []
  },
  {
    "type": "error",
    "name": "NotDeployer",
    "inputs": []
  },
  {
    "type": "error",
    "name": "NotHumansToken",
    "inputs": []
  },
  {
    "type": "error",
    "name": "NotMarket",
    "inputs": []
  },
  {
    "type": "error",
    "name": "NotXpegOwner",
    "inputs": []
  },
  {
    "type": "error",
    "name": "RendererAlreadySet",
    "inputs": []
  },
  {
    "type": "error",
    "name": "RendererUnset",
    "inputs": []
  },
  {
    "type": "error",
    "name": "TokenAlreadySet",
    "inputs": []
  },
  {
    "type": "error",
    "name": "UpegIndexOutOfRange",
    "inputs": []
  },
  {
    "type": "error",
    "name": "ZeroAddress",
    "inputs": []
  }
]